setup.py
dm/__init__.py
dm.zopepatches.security.egg-info/PKG-INFO
dm.zopepatches.security.egg-info/SOURCES.txt
dm.zopepatches.security.egg-info/dependency_links.txt
dm.zopepatches.security.egg-info/namespace_packages.txt
dm.zopepatches.security.egg-info/not-zip-safe
dm.zopepatches.security.egg-info/top_level.txt
dm/zopepatches/__init__.py
dm/zopepatches/security/README.txt
dm/zopepatches/security/VERSION.txt
dm/zopepatches/security/__init__.py
dm/zopepatches/security/proxy.py
dm/zopepatches/security/tests/__init__.py
dm/zopepatches/security/tests/test_proxy.py