Metadata-Version: 1.1
Name: dm.zopepatches.security
Version: 2.0
Summary: Workarounds related to Zope's security subsystem.
Home-page: http://pypi.python.org/pypi/dm.zopepatches.security
Author: Dieter Maurer
Author-email: dieter@handshake.de
License: BSD
Keywords: application development menu web security proxy
Platform: UNKNOWN
Classifier: Development Status :: 5 - Production/Stable
Classifier: Intended Audience :: Developers
Classifier: License :: OSI Approved :: Zope Public License
Classifier: Framework :: Zope2
Classifier: Operating System :: OS Independent
Classifier: Programming Language :: Python
Classifier: Topic :: Utilities
